{
    "rdc1_full_scale_value": 5321564160,
    "rdc2_full_scale_value": 5364136673280,
    "rdc2ch_full_scale_value": 383152619520,
    "rdc3_full_scale_value": 268206833664000,
    "scan_sequence_number": 1,
    "scan_ID_number": 1,
    "scan_timestamp": 242756908,
    "current_time": 242788499,
    "device_id": 21930,
    "sample_rate": 968750016.0,
    "num_range_bins": 128,
    "num_pulses": 1008,
    "total_vrx": 64,
    "num_beamforming_angles": 128,
    "num_channelizer_iters": 25,
    "num_channelizer_doppler_bins": 72,
    "num_detections": 16,
    "SS_size_R": 128,
    "SS_size_A": 128,
    "SS_size_D": 7,
    "CI_width": 128,
    "CI_height": 128,
    "CI_doppler_width": 128,
    "CI_doppler_height": 128,
    "CI_pixel_size_in_meters": 0.30946317315101626,
    "CI_bytes_per_pixel": 2,
    "CI_format": 7,
    "rdc1_software_exponent": 4,
    "rdc2_software_exponent": 2,
    "rdc3_software_exponent": 6,
    "clutter_image_exponent": 18,
    "system_exponent": 0,
    "overflow_underflow_flags": 0,
    "num_music_instances": 0,
    "angle_wrap_flags": 0,
    "num_angle_groups": 1,
    "scan_time": 0.02344074659049511,
    "pulse_time": 0.00002325470995856449,
    "chip_time": 2.0645161136201297e-9,
    "doppler_bin_width": 0.08251208066940308,
    "range_bin_width": 0.30946317315101626,
    "chips_per_pulse": 11264,
    "code_type": 1,
    "vp_scan_mode": 0,
    "ego_velocity_X": 0.0,
    "ego_velocity_Y": 0.0,
    "ego_velocity_Z": 0.0,
    "estimated_ego_velocity_X": 0.0,
    "estimated_ego_velocity_Y": 0.0,
    "estimated_ego_velocity_Z": 0.0,
    "num_azimuth_angles": 128,
    "azimuth_nyquist_oversampling_factor": 3,
    "elevation_nyquist_oversampling_factor": 1,
    "chip_temp_C": 56.07924270629883,
    "chip_LO_temp_C": 0.0,
    "board_T3_temp_C": 38.4375,
    "total_points": 0,
    "rdc2_zd_rb_center": 0,
    "rdc2_zd_rb_halfwidth": 0,
    "activation_filter_snr": 0.0,
    "radar_status_bitmap": 47927,
    "antenna_config_id": 0,
    "num_tx_prn": 8,
    "rb_combine": 1,
    "carrier_frequency": 77.5,
    "vrx_position_offset_X": 0.0,
    "vrx_position_offset_Y": -0.03932249918580055,
    "vrx_position_offset_Z": -0.03990200161933899,
    "vrx_map": [1, 4, 8, 13, 32, 36, 40, 45, 3, 7, 12, 17, 35, 39, 44, 49, 0, 2, 5, 9, 29, 33, 37, 41, 6, 11, 16, 21, 38, 43, 48, 53, 18, 23, 27, 31, 50, 55, 59, 62, 10, 15, 20, 25, 42, 47, 52, 57, 22, 26, 30, 34, 54, 58, 61, 63, 14, 19, 24, 28, 46, 51, 56, 60],
    "host_datetime": "2020-03-31 10:56:59.991904",
    "dc_bias": [0.4162801206111908, 1.1183267831802369, 0.5074869990348816, -0.118682861328125, -0.7522684931755066, 2.423492431640625, 0.1505839079618454, 0.2889607846736908, -1.755828857421875, 0.9655049443244934, 0.288909912109375, 0.008646647445857525, -0.579803466796875, 1.1365865468978882, -0.8668314814567566, -1.5475870370864869, 0.0, 0.0, 0.0, 0.0, 0.0, 0.0, 0.0, 0.0, 0.0, 0.0, 0.0, 0.0, 0.0, 0.0, 0.0, 0.0],
    "srs_version": "srs-v0.6.3-BF6+0-864cc25dd2bc",
    "module_name": "JDO-5-004",
    "module_type_name": "Judo",
    "motherboard_type_name": "PIB48",
    "antennaboard_type_name": "ADB2",
    "antenna_module_type_name": "ADB2",
    "thresholds": {
        "static_1D_thresh_snr_dB": 15.0,
        "moving_1D_thresh_snr_dB": 16.0,
        "static_2D_thresh_snr_dB": 16.0,
        "moving_2D_thresh_snr_dB": 17.0,
        "scale_det_thresh_max_range": 15.0,
        "scale_det_thresh_snr_adj": 4.0,
        "base_static_snr_dB": 12.0,
        "base_moving_snr_dB": 12.0,
        "notch_width_radians": 0.471238911151886,
        "notch_depth_dB": 10.0,
        "outer_depth_dB": 7.0,
        "ridge_threshold_dB": 9.0,
        "phased_array_azimuth": 0.0
    },
    "tx_pos": [0.0, -0.014582499861717224, 0.03990199416875839, -0.00870249792933464, 0.03990199416875839, 0.0, 0.03990199416875839, 0.0, -0.0028224997222423555, 0.0, 0.014817502349615097, 0.03990199416875839, 0.0030575022101402284, 0.03990199416875839, 0.0, 0.03990199416875839, 0.0, 0.008937504142522812, 1.0193878802084993e-38, 1.0653071697158056e-38, 1.010204610852393e-38, 1.0561244608790851e-38, 0.0, 0.0],
    "rx_pos": [0.0, -0.03932249918580055, -0.03990200161933899, -0.031482499092817309, -0.03990200161933899, 0.0, -0.03990200161933899, 0.0, -0.015802498906850816, 0.0, 0.01556750014424324, -0.03990200161933899, 0.023407500237226487, -0.03990200161933899, 0.0, -0.03990200161933899, 0.0, 0.03908750042319298, 1.0193751283924739e-38, 0.0, 0.0, 4.5000009688739999e-39, 0.0, 0.0],
    "mount_geometry": [3.9100000858306886, 0.0, 0.699999988079071, 0.0, 0.0],
    "sra_version": "rra-v0.6.3-BF6+0-9c3f1dc3fdd2"
}